ai18n/__init__.py
ai18n/cli.py
ai18n/config.py
ai18n/constants.py
ai18n/message.py
ai18n/openai.py
ai18n/translator.py
ai18n/templates/prompt.jinja
ai18n-0.3.1.dist-info/LICENSE
ai18n-0.3.1.dist-info/METADATA
ai18n-0.3.1.dist-info/WHEEL
ai18n-0.3.1.dist-info/entry_points.txt
ai18n-0.3.1.dist-info/top_level.txt
ai18n-0.3.1.dist-info/RECORD
