Metadata-Version: 2.1
Name: ai18n
Version: 0.3.1
Summary: A tool for managing and automating translations with OpenAI and PO files
Author-email: Max <max@preset.io>
License: Apache-2.0
Requires-Python: >=3.7
License-File: LICENSE
Requires-Dist: jinja2
Requires-Dist: openai
Requires-Dist: polib
Requires-Dist: pyyaml
